pycode/__init__.py
pycode/cli.py
pycode/coding_unit.py
pycode/config.py
pycode/core.py
pycode/main.py
pycode/persistance.py
pycode/persistence.py
pycode/pycode.py
pycode/utils.py
pycode/gui/__init__.py
pycode/gui/coding_unit.py
pycode/gui/core.py
pycode/gui/dialogs.py
pycode/gui/presenter.py
pycode/gui/widgets.py
pycode-0.1.2.dist-info/DESCRIPTION.rst
pycode-0.1.2.dist-info/METADATA
pycode-0.1.2.dist-info/RECORD
pycode-0.1.2.dist-info/WHEEL
pycode-0.1.2.dist-info/entry_points.txt
pycode-0.1.2.dist-info/metadata.json
pycode-0.1.2.dist-info/top_level.txt
tests/__init__.py
tests/jerome.txt
tests/test_gui_core.py
tests/test_gui_widgets.py
tests/test_main.py
tests/test_persistence.py
tests/test_pycode.py
tests/test_utils.py
