Metadata-Version: 1.1
Name: pycode
Version: 0.1.2
Summary: Python tool for research coding
Home-page: https://github.com/j340m3/pycode
Author: Jerome Bergmann
Author-email: jerome.bergmann@rwth-aachen.de
License: GNU General Public License v3
Keywords: pycode
Platform: any
Classifier: Development Status :: 2 - Pre-Alpha
Classifier: Intended Audience :: Developers
Classifier: License :: OSI Approved :: GNU General Public License (GPL)
Classifier: Natural Language :: English
Classifier: Programming Language :: Python :: 2
Classifier: Programming Language :: Python :: 2.6
Classifier: Programming Language :: Python :: 2.7
Classifier: Programming Language :: Python :: 3
Classifier: Programming Language :: Python :: 3.3
Classifier: Programming Language :: Python :: 3.4
Classifier: Programming Language :: Python :: 3.5
